shell_interface/__init__.py
shell_interface/py.typed
shell_interface/shell_interface.py
shell_interface-1.0.2.dist-info/METADATA
shell_interface-1.0.2.dist-info/WHEEL
shell_interface-1.0.2.dist-info/licenses/LICENSE
shell_interface-1.0.2.dist-info/RECORD
