Metadata-Version: 2.4
Name: shell-interface
Version: 1.0.2
Summary: Helpful and convenient utilities to interact with UNIX shells
License-Expression: GPL-3.0-or-later
License-File: LICENSE
Author: Max Görner
Author-email: 5477952+MaxG87@users.noreply.github.com
Requires-Python: >=3.9
Classifier: Programming Language :: Python :: 3
Classifier: Programming Language :: Python :: 3.9
Classifier: Programming Language :: Python :: 3.10
Classifier: Programming Language :: Python :: 3.11
Classifier: Programming Language :: Python :: 3.12
Classifier: Programming Language :: Python :: 3.13
Classifier: Programming Language :: Python :: 3.14
Provides-Extra: logging
Requires-Dist: loguru ; extra == "logging"
Project-URL: Changelog, https://github.com/MaxG87/shell-interface/blob/main/CHANGELOG.md
Project-URL: Homepage, https://github.com/MaxG87/shell-interface
Project-URL: Issues, https://github.com/MaxG87/shell-interface/issues
Project-URL: Repository, https://github.com/MaxG87/shell-interface
